README.md
setup.cfg
setup.py
k8s_functions/__init__.py
k8s_functions/functions.py
k8s_functions/test_functions.py
k8s_subjects_storage/__init__.py
k8s_subjects_storage/storage_impl.py
k8s_subjects_storage/test_storage.py
k8s_subjects_storage/test_with_subject.py
krules_subjects_storage_k8s.egg-info/PKG-INFO
krules_subjects_storage_k8s.egg-info/SOURCES.txt
krules_subjects_storage_k8s.egg-info/dependency_links.txt
krules_subjects_storage_k8s.egg-info/requires.txt
krules_subjects_storage_k8s.egg-info/top_level.txt